README.md
setup.py
TurnonModbusTCP/__init__.py
TurnonModbusTCP/communication.py
TurnonModbusTCP/error.py
TurnonModbusTCP/get.py
TurnonModbusTCP/gripper.py
TurnonModbusTCP/gripper_move.py
TurnonModbusTCP/logger.py
TurnonModbusTCP/modbus.py
TurnonModbusTCP/modbus_client.py
TurnonModbusTCP/modbus_server.py
TurnonModbusTCP/motion.py
TurnonModbusTCP/motion_config.py
TurnonModbusTCP/motion_move.py
TurnonModbusTCP.egg-info/PKG-INFO
TurnonModbusTCP.egg-info/SOURCES.txt
TurnonModbusTCP.egg-info/dependency_links.txt
TurnonModbusTCP.egg-info/requires.txt
TurnonModbusTCP.egg-info/top_level.txt