Metadata-Version: 2.1
Name: TurnonModbusTCP
Version: 0.0.24
Summary: Turnon-Tech for Franka Modbus
Home-page: http://pypi.org/user/n159951357753/
Author: Kevin Wang
Author-email: n159951357753159@gmail.com
License: MIT
Platform: UNKNOWN
Requires-Python: >=3.6
